bit2LessThanEqualTo.v
module bit2LessThanEqualTo(
    input [1:0] A,
    input [1:0] B,
    output wire Y
);
wire w1,w2,w5,w6,w7,w8,w9,w10,w11,w12,w13;
assign w1= ~(A[1]);
assign w2= ~(A[0]);


and a1 (w5,w1,B[1]);
and a2 (w6,w2,B[0]);
and a3 (w7,w6,w8);
and a4(w10,w12,w9);
or o1(w8,B[1],w1);
or o2(w11,w7,w5);
or o3(w13,w10,w11);
xnor x1(w9,B[1],A[1]);
xnor x2(w12,B[0],A[0]);
assign Y=w13;
endmodule

tb_2bitLessThanEqualTo.v
module tb_bit2LessThanEqualTo;
  reg  [1:0] A, B;
  wire Y;
  reg expected; 
   bit2LessThanEqualTo uut (.A(A),.B(B),.Y(Y));
   integer i, j;

    initial begin
        $dumpfile("bit2LessThanEqualTo.vcd");
        $dumpvars(0, tb_bit2LessThanEqualTo);
        $display("========================================");
        $display(" A   B   Y   Expected   Status");
        $display("========================================");

        for (i = 0; i < 4; i = i + 1) begin
            for (j = 0; j < 4; j = j + 1) begin

                A = i;
                B = j;
                #10;

                expected = (A <= B);

                if (Y == expected)
                    $display("%2d  %2d   %b      %b       PASS",
                             A, B, Y, expected);
                else
                    $display("%2d  %2d   %b      %b       FAIL",
                             A, B, Y, expected);

            end
        end
        $finish;

  end
endmodule

bit2LessThanEqualTo.vcd
$date
	Fri Aug 07 17:27:39 2026
$end
$version
	Icarus Verilog
$end
$timescale
	1s
$end
$scope module tb_bit2LessThanEqualTo $end
$var wire 1 ! Y $end
$var reg 2 " A [1:0] $end
$var reg 2 # B [1:0] $end
$var reg 1 $ expected $end
$var integer 32 % i [31:0] $end
$var integer 32 & j [31:0] $end
$scope module uut $end
$var wire 2 ' A [1:0] $end
$var wire 2 ( B [1:0] $end
$var wire 1 ! Y $end
$var wire 1 ) w1 $end
$var wire 1 * w10 $end
$var wire 1 + w11 $end
$var wire 1 , w12 $end
$var wire 1 - w13 $end
$var wire 1 . w2 $end
$var wire 1 / w5 $end
$var wire 1 0 w6 $end
$var wire 1 1 w7 $end
$var wire 1 2 w8 $end
$var wire 1 3 w9 $end
$upscope $end
$upscope $end
$enddefinitions $end
#0
$dumpvars
13
12
01
00
0/
1.
1-
1,
0+
1*
1)
b0 (
b0 '
b0 &
b0 %
x$
b0 #
b0 "
1!
$end
#10
1+
1!
1-
11
0*
10
0,
b1 #
b1 (
b1 &
1$
#20
01
1/
00
03
1,
b10 #
b10 (
b10 &
#30
11
10
0,
b11 #
b11 (
b11 &
#40
0!
0-
0+
01
0/
00
13
0.
b0 #
b0 (
b1 "
b1 '
b1 %
b0 &
#50
1!
1-
1*
1,
b1 #
b1 (
b1 &
0$
#60
1+
0*
1/
03
0,
b10 #
b10 (
b10 &
1$
#70
1,
b11 #
b11 (
b11 &
#80
0!
0-
0+
0/
02
0)
1.
b0 #
b0 (
b10 "
b10 '
b10 %
b0 &
#90
10
0,
b1 #
b1 (
b1 &
0$
#100
1!
1-
1*
00
12
13
1,
b10 #
b10 (
b10 &
#110
1+
1!
1-
11
0*
10
0,
b11 #
b11 (
b11 &
1$
#120
0!
0-
0+
01
00
02
03
0.
b0 #
b0 (
b11 "
b11 '
b11 %
b0 &
#130
1,
b1 #
b1 (
b1 &
0$
#140
12
13
0,
b10 #
b10 (
b10 &
#150
1!
1-
1*
1,
b11 #
b11 (
b11 &
#160
b100 %
b100 &
1$
