quat_suc.v
module quat_suc(
  input  [1:0] A,
  output [1:0] Y
);
  assign Y = A + 2'b01; // 2-bit overflow = automatic mod 4
endmodule

bit2LessThanEqualTo.v
module bit2LessThanEqualTo(
    input [1:0] A,
    input [1:0] B,
    output wire Y
);
wire w1,w2,w5,w6,w7,w8,w9,w10,w11,w12,w13;
assign w1= ~(A[1]);
assign w2= ~(A[0]);


and a1 (w5,w1,B[1]);
and a2 (w6,w2,B[0]);
and a3 (w7,w6,w8);
and a4(w10,w12,w9);
or o1(w8,B[1],w1);
or o2(w11,w7,w5);
or o3(w13,w10,w11);
xnor x1(w9,B[1],A[1]);
xnor x2(w12,B[0],A[0]);
assign Y=w13;
endmodule

quat_min.v

module quat_min(
  input  [1:0] A,
  input  [1:0] B,
  output [1:0] Y
);
wire sel;
bit2LessThanEqualTo U1 (
    .A(A),
    .B(B),
    .Y(sel)
);
assign Y = (sel) ? A : B;
endmodule

quat_max.v

module quat_max(
  input  [1:0] A,
  input  [1:0] B,
  output [1:0] Y
);
  assign Y = (A >= B) ? A : B;
endmodule

quat_full_adder.v
module quat_full_adder(
  input  [1:0] A,
  input  [1:0] B,
  input  [1:0] Cin,
  output [1:0] Sum,
  output [1:0] Cout
);
  wire [3:0] total;
  assign total = {2'b00, A} + {2'b00, B} + {2'b00, Cin};
  assign Sum   = total[1:0];
  assign Cout  = total[3:2];
endmodule

quat_add4.v
module quat_add4(
  input  [7:0] A,
  input  [7:0] B,
  output [7:0] Sum,
  output [1:0] Cout
);
  // A = {q3,q2,q1,q0} each 2 bits
  // Add digit by digit with carry chain

  wire [1:0] a0,a1,a2,a3;
  wire [1:0] b0,b1,b2,b3;
  wire [1:0] s0,s1,s2,s3;
  wire [1:0] c1,c2,c3;

  // Unpack digits
  assign a0 = A[1:0]; assign b0 = B[1:0];
  assign a1 = A[3:2]; assign b1 = B[3:2];
  assign a2 = A[5:4]; assign b2 = B[5:4];
  assign a3 = A[7:6]; assign b3 = B[7:6];

  // 4 full adders in ripple carry chain
  quat_full_adder FA0(.A(a0),.B(b0),.Cin(2'b00),.Sum(s0),.Cout(c1));
  quat_full_adder FA1(.A(a1),.B(b1),.Cin(c1),   .Sum(s1),.Cout(c2));
  quat_full_adder FA2(.A(a2),.B(b2),.Cin(c2),   .Sum(s2),.Cout(c3));
  quat_full_adder FA3(.A(a3),.B(b3),.Cin(c3),   .Sum(s3),.Cout(Cout));

  // Pack result
  assign Sum = {s3,s2,s1,s0};
endmodule

quat_alu_wide.v
module quat_alu_wide(
  input  [7:0] A,
  input  [7:0] B,
  input  [2:0] opcode,
  output reg [7:0] Result,
  output reg       Zero,
  output reg       Carry
);
  // 4-digit operations
  wire [7:0] add_sum;
  wire [1:0] add_cout;

  // MAX and MIN digit by digit
  wire [1:0] max0,max1,max2,max3;
  wire [1:0] min0,min1,min2,min3;

  // SUC on each digit
  wire [1:0] suc0,suc1,suc2,suc3;

  // Instantiate 4-digit adder
  quat_add4 ADD4(
    .A(A),.B(B),
    .Sum(add_sum),.Cout(add_cout)
  );

  // MAX digit by digit
  quat_max MX0(.A(A[1:0]),.B(B[1:0]),.Y(max0));
  quat_max MX1(.A(A[3:2]),.B(B[3:2]),.Y(max1));
  quat_max MX2(.A(A[5:4]),.B(B[5:4]),.Y(max2));
  quat_max MX3(.A(A[7:6]),.B(B[7:6]),.Y(max3));

  // MIN digit by digit
  quat_min MN0(.A(A[1:0]),.B(B[1:0]),.Y(min0));
  quat_min MN1(.A(A[3:2]),.B(B[3:2]),.Y(min1));
  quat_min MN2(.A(A[5:4]),.B(B[5:4]),.Y(min2));
  quat_min MN3(.A(A[7:6]),.B(B[7:6]),.Y(min3));

  // SUC digit by digit
  quat_suc SC0(.A(A[1:0]),.Y(suc0));
  quat_suc SC1(.A(A[3:2]),.Y(suc1));
  quat_suc SC2(.A(A[5:4]),.Y(suc2));
  quat_suc SC3(.A(A[7:6]),.Y(suc3));

  always @(*) begin
    Carry = 0;
    case(opcode)
      3'b000: begin                          // ADD all 4 digits
                Result = add_sum;
                Carry  = (add_cout > 0);
              end
      3'b001: Result = {max3,max2,max1,max0}; // MAX per digit
      3'b010: Result = {min3,min2,min1,min0}; // MIN per digit
      3'b011: Result = {suc3,suc2,suc1,suc0}; // SUC per digit
      3'b100: begin                            // Compare MSB digit
                Result = (A > B) ? 8'd1 : 8'd0;
              end
      3'b101: begin                            // Equal check
                Result = (A == B) ? 8'd3 : 8'd0;
              end
      3'b110: Result = A;                      // PASS A (for MOV)
      3'b111: Result = 8'd0;                   // ZERO
      default: Result = 8'd0;
    endcase
    Zero = (Result == 8'd0);
  end
endmodule

quat_control16.v
module quat_control16(
  input  [3:0] opcode,
  output reg [2:0] alu_op,
  output reg       reg_write,
  output reg       is_mov
);
  always @(*) begin
    alu_op    = 3'b000;
    reg_write = 1'b0;
    is_mov    = 1'b0;

    case(opcode)
      4'b0000: begin alu_op=3'b000; reg_write=1'b1; end // ADD
      4'b0001: begin alu_op=3'b001; reg_write=1'b1; end // MAX
      4'b0010: begin alu_op=3'b010; reg_write=1'b1; end // MIN
      4'b0011: begin alu_op=3'b000; reg_write=1'b1;     // MOV
                     is_mov=1'b1; end
      4'b0100: begin alu_op=3'b100; reg_write=1'b1; end // TSUM
      4'b0101: begin alu_op=3'b110; reg_write=1'b1; end // CMP
      4'b0110: begin reg_write=1'b0; end                 // NOP
      default: begin reg_write=1'b0; end
    endcase
  end
endmodule

quat_regfile.v
module quat_regfile(
  input        clk,
  input        rst,
  input        we,
  input  [3:0] rd_addr1,
  input  [3:0] rd_addr2,
  input  [3:0] wr_addr,
  input  [7:0] wr_data,
  output [7:0] rd_data1,
  output [7:0] rd_data2
);
  reg [7:0] regs [0:15];
  integer i;
  initial begin
    for(i = 0; i < 16; i = i + 1)
    regs[i] = 8'd0;
    // Seed for Fibonacci: r0=0, r1=1
    regs[0] = 8'b00_00_00_00;
    regs[1] = 8'b00_00_00_01;
    end
    always @(posedge clk or posedge rst) begin
      if(rst) begin
        for(i = 0; i < 16; i = i + 1)
        regs[i] <= 8'd0;
        regs[1] <= 8'd1;
        end
        else if(we)
        regs[wr_addr] <= wr_data;
        end
        assign rd_data1 = regs[rd_addr1];
        assign rd_data2 = regs[rd_addr2];
endmodule

quat_imem16.v
module quat_imem16(
  input  [3:0] addr,
  output [15:0] instr
);
  reg [15:0] mem [0:15];
  initial begin
    mem[0]  = 16'b0000_0000_0001_0010; // ADD r2=r0+r1
    mem[1]  = 16'b0110_0000_0000_0000; // NOP (wait for r2)
    mem[2]  = 16'b0110_0000_0000_0000; // NOP (wait for r2)
    mem[3]  = 16'b0011_0001_0000_0000; // MOV r0=r1
    mem[4]  = 16'b0011_0010_0000_0001; // MOV r1=r2
    mem[5]  = 16'b0110_0000_0000_0000; // NOP
    mem[6]  = 16'b0000_0000_0001_0010; // ADD r2=r0+r1
    mem[7]  = 16'b0110_0000_0000_0000; // NOP
    mem[8]  = 16'b0110_0000_0000_0000; // NOP
    mem[9]  = 16'b0011_0001_0000_0000; // MOV r0=r1
    mem[10] = 16'b0011_0010_0000_0001; // MOV r1=r2
    mem[11] = 16'b0110_0000_0000_0000; // NOP
    mem[12] = 16'b0000_0000_0001_0010; // ADD r2=r0+r1
    mem[13] = 16'b0110_0000_0000_0000; // NOP
    mem[14] = 16'b0110_0000_0000_0000; // NOP
    mem[15] = 16'b0110_0000_0000_0000; // NOP
    end
  assign instr = mem[addr];
endmodule

quat_cpu16.v
module quat_cpu16(
  input clk,
  input rst
);
  // Program Counter
  reg [3:0] PC;

  // Pipeline registers IF/ID
  reg [15:0] IF_ID_instr;

  // Pipeline registers ID/EX
  reg [15:0] ID_EX_instr;
  reg [7:0]  ID_EX_rs1_data;
  reg [7:0]  ID_EX_rs2_data;
  reg [2:0] ID_EX_alu_op;
  reg       ID_EX_reg_write;
  reg       ID_EX_is_mov;

  // Pipeline registers EX/WB
  reg [7:0]  EX_WB_result;
  reg [3:0]  EX_WB_rd;
  reg        EX_WB_reg_write;

  // Instruction fields
  wire [3:0] opcode = IF_ID_instr[15:12];
  wire [3:0] rs1    = IF_ID_instr[11:8];
  wire [3:0] rs2    = IF_ID_instr[7:4];
  wire [3:0] rd     = IF_ID_instr[3:0];

  // Control signals
  wire [2:0] alu_op;
  wire       reg_write, is_mov;

  // Data wires
  wire [15:0] instr;
  wire [7:0]  rs1_data, rs2_data;
  wire [7:0]  alu_result_wide;
  wire        zero, carry;

  // Modules
  quat_imem16 IMEM(.addr(PC), .instr(instr));

  quat_regfile RF(
    .clk(clk), .rst(rst),
    .we(EX_WB_reg_write),
    .rd_addr1(rs1),
    .rd_addr2(rs2),
    .wr_addr(EX_WB_rd),
    .wr_data(EX_WB_result),
    .rd_data1(rs1_data),
    .rd_data2(rs2_data)
  );

  quat_control16 CTRL(
    .opcode(opcode),
    .alu_op(alu_op),
    .reg_write(reg_write),
    .is_mov(is_mov)
  );

  quat_alu_wide ALU(
    .A(ID_EX_rs1_data),
    .B(ID_EX_rs2_data),
    .opcode(ID_EX_alu_op),
    .Result(alu_result_wide),
    .Zero(zero),
    .Carry(carry)
  );

  // IF Stage
  always @(posedge clk or posedge rst) begin
    if(rst) begin
      PC          <= 4'd0;
      IF_ID_instr <= 16'd0;
    end else begin
      IF_ID_instr <= instr;
      PC          <= PC + 1;
    end
  end

  // ID Stage
  always @(posedge clk or posedge rst) begin
    if(rst) begin
      ID_EX_instr    <= 16'd0;
      ID_EX_rs1_data <= 8'd0;
      ID_EX_rs2_data <= 8'd0;
      ID_EX_alu_op     <= 3'b000;
      ID_EX_reg_write  <= 1'b0;
      ID_EX_is_mov     <= 1'b0;
    end else begin
      ID_EX_instr    <= IF_ID_instr;
      ID_EX_rs1_data <= rs1_data;
      ID_EX_rs2_data <= rs2_data;
      ID_EX_alu_op     <= alu_op;
      ID_EX_reg_write  <= reg_write;
      ID_EX_is_mov     <= is_mov;

    end
  end

  // EX + WB Stage
  always @(posedge clk or posedge rst) begin
    if(rst) begin
      EX_WB_result    <= 8'd0;
      EX_WB_rd        <= 4'd0;
      EX_WB_reg_write <= 1'b0;
    end else begin
      if(ID_EX_is_mov)
        EX_WB_result <= ID_EX_rs1_data;
      else
        EX_WB_result <=  alu_result_wide;
      EX_WB_rd        <= ID_EX_instr[3:0];
      EX_WB_reg_write <= ID_EX_reg_write;
    end
  end

endmodule

tb_cpu16.v
module tb_cpu16;
  reg clk, rst;
  integer cycle;

  quat_cpu16 CPU(.clk(clk), .rst(rst));

  always #5 clk = ~clk;

  wire [7:0] r0 = CPU.RF.regs[0];
  wire [7:0] r1 = CPU.RF.regs[1];
  wire [7:0] r2 = CPU.RF.regs[2];

  initial begin
    $dumpfile("dump.vcd");
    $dumpvars(0, tb_cpu16);
    clk = 0; rst = 1; cycle = 0;
    // Hold reset for 4 clock cycles
    #40 rst = 0;
    $display("=== 16-BIT QUATERNARY CPU - FIBONACCI ===");
    $display("Cycle | PC | Opcode | isMOV | R0 | R1 | R2");
    $display("------+----+--------+-------+----+----+---");

    repeat(24) begin
      @(posedge clk); #1;
      cycle = cycle + 1;
      $display("  %2d  | %2d |  %4b  |   %1b   | %2d | %2d | %2d",
               cycle,
               CPU.PC,
               CPU.ID_EX_instr[15:12],
               CPU.ID_EX_is_mov,
               r0[1:0],
               r1[1:0],
               r2[1:0]);
    end

    $display("------+----+--------+-------+----+----+---");
    $display("FINAL: R0=%0d R1=%0d R2=%0d",
             r0[1:0], r1[1:0], r2[1:0]);
    $display("Fibonacci in quaternary: 0,1,1,2,3");
    $display("=== DONE ===");
    $finish;
  end
endmodule

dump.vcd
$date
	Sat Aug 01 17:21:34 2026
$end
$version
	Icarus Verilog
$end
$timescale
	1s
$end
$scope module tb_cpu16 $end
$var wire 8 ! r0 [7:0] $end
$var wire 8 " r1 [7:0] $end
$var wire 8 # r2 [7:0] $end
$var reg 1 $ clk $end
$var reg 1 % rst $end
$var integer 32 & cycle [31:0] $end
$scope module CPU $end
$var wire 1 $ clk $end
$var wire 1 % rst $end
$var wire 1 ' zero $end
$var wire 8 ( rs2_data [7:0] $end
$var wire 4 ) rs2 [3:0] $end
$var wire 8 * rs1_data [7:0] $end
$var wire 4 + rs1 [3:0] $end
$var wire 1 , reg_write $end
$var wire 4 - rd [3:0] $end
$var wire 4 . opcode [3:0] $end
$var wire 1 / is_mov $end
$var wire 16 0 instr [15:0] $end
$var wire 1 1 carry $end
$var wire 8 2 alu_result_wide [7:0] $end
$var wire 3 3 alu_op [2:0] $end
$var reg 4 4 EX_WB_rd [3:0] $end
$var reg 1 5 EX_WB_reg_write $end
$var reg 8 6 EX_WB_result [7:0] $end
$var reg 3 7 ID_EX_alu_op [2:0] $end
$var reg 16 8 ID_EX_instr [15:0] $end
$var reg 1 9 ID_EX_is_mov $end
$var reg 1 : ID_EX_reg_write $end
$var reg 8 ; ID_EX_rs1_data [7:0] $end
$var reg 8 < ID_EX_rs2_data [7:0] $end
$var reg 16 = IF_ID_instr [15:0] $end
$var reg 4 > PC [3:0] $end
$scope module ALU $end
$var wire 8 ? A [7:0] $end
$var wire 8 @ B [7:0] $end
$var wire 3 A opcode [2:0] $end
$var wire 2 B suc3 [1:0] $end
$var wire 2 C suc2 [1:0] $end
$var wire 2 D suc1 [1:0] $end
$var wire 2 E suc0 [1:0] $end
$var wire 2 F min3 [1:0] $end
$var wire 2 G min2 [1:0] $end
$var wire 2 H min1 [1:0] $end
$var wire 2 I min0 [1:0] $end
$var wire 2 J max3 [1:0] $end
$var wire 2 K max2 [1:0] $end
$var wire 2 L max1 [1:0] $end
$var wire 2 M max0 [1:0] $end
$var wire 8 N add_sum [7:0] $end
$var wire 2 O add_cout [1:0] $end
$var reg 1 1 Carry $end
$var reg 8 P Result [7:0] $end
$var reg 1 ' Zero $end
$scope module ADD4 $end
$var wire 8 Q A [7:0] $end
$var wire 8 R B [7:0] $end
$var wire 2 S s3 [1:0] $end
$var wire 2 T s2 [1:0] $end
$var wire 2 U s1 [1:0] $end
$var wire 2 V s0 [1:0] $end
$var wire 2 W c3 [1:0] $end
$var wire 2 X c2 [1:0] $end
$var wire 2 Y c1 [1:0] $end
$var wire 2 Z b3 [1:0] $end
$var wire 2 [ b2 [1:0] $end
$var wire 2 \ b1 [1:0] $end
$var wire 2 ] b0 [1:0] $end
$var wire 2 ^ a3 [1:0] $end
$var wire 2 _ a2 [1:0] $end
$var wire 2 ` a1 [1:0] $end
$var wire 2 a a0 [1:0] $end
$var wire 8 b Sum [7:0] $end
$var wire 2 c Cout [1:0] $end
$scope module FA0 $end
$var wire 2 d A [1:0] $end
$var wire 2 e B [1:0] $end
$var wire 2 f Cin [1:0] $end
$var wire 4 g total [3:0] $end
$var wire 2 h Sum [1:0] $end
$var wire 2 i Cout [1:0] $end
$upscope $end
$scope module FA1 $end
$var wire 2 j A [1:0] $end
$var wire 2 k B [1:0] $end
$var wire 2 l Cin [1:0] $end
$var wire 4 m total [3:0] $end
$var wire 2 n Sum [1:0] $end
$var wire 2 o Cout [1:0] $end
$upscope $end
$scope module FA2 $end
$var wire 2 p A [1:0] $end
$var wire 2 q B [1:0] $end
$var wire 2 r Cin [1:0] $end
$var wire 4 s total [3:0] $end
$var wire 2 t Sum [1:0] $end
$var wire 2 u Cout [1:0] $end
$upscope $end
$scope module FA3 $end
$var wire 2 v A [1:0] $end
$var wire 2 w B [1:0] $end
$var wire 2 x Cin [1:0] $end
$var wire 4 y total [3:0] $end
$var wire 2 z Sum [1:0] $end
$var wire 2 { Cout [1:0] $end
$upscope $end
$upscope $end
$scope module MN0 $end
$var wire 2 | A [1:0] $end
$var wire 2 } B [1:0] $end
$var wire 1 ~ sel $end
$var wire 2 !" Y [1:0] $end
$scope module U1 $end
$var wire 2 "" A [1:0] $end
$var wire 2 #" B [1:0] $end
$var wire 1 ~ Y $end
$var wire 1 $" w1 $end
$var wire 1 %" w10 $end
$var wire 1 &" w11 $end
$var wire 1 '" w12 $end
$var wire 1 (" w13 $end
$var wire 1 )" w2 $end
$var wire 1 *" w5 $end
$var wire 1 +" w6 $end
$var wire 1 ," w7 $end
$var wire 1 -" w8 $end
$var wire 1 ." w9 $end
$upscope $end
$upscope $end
$scope module MN1 $end
$var wire 2 /" A [1:0] $end
$var wire 2 0" B [1:0] $end
$var wire 1 1" sel $end
$var wire 2 2" Y [1:0] $end
$scope module U1 $end
$var wire 2 3" A [1:0] $end
$var wire 2 4" B [1:0] $end
$var wire 1 1" Y $end
$var wire 1 5" w1 $end
$var wire 1 6" w10 $end
$var wire 1 7" w11 $end
$var wire 1 8" w12 $end
$var wire 1 9" w13 $end
$var wire 1 :" w2 $end
$var wire 1 ;" w5 $end
$var wire 1 <" w6 $end
$var wire 1 =" w7 $end
$var wire 1 >" w8 $end
$var wire 1 ?" w9 $end
$upscope $end
$upscope $end
$scope module MN2 $end
$var wire 2 @" A [1:0] $end
$var wire 2 A" B [1:0] $end
$var wire 1 B" sel $end
$var wire 2 C" Y [1:0] $end
$scope module U1 $end
$var wire 2 D" A [1:0] $end
$var wire 2 E" B [1:0] $end
$var wire 1 B" Y $end
$var wire 1 F" w1 $end
$var wire 1 G" w10 $end
$var wire 1 H" w11 $end
$var wire 1 I" w12 $end
$var wire 1 J" w13 $end
$var wire 1 K" w2 $end
$var wire 1 L" w5 $end
$var wire 1 M" w6 $end
$var wire 1 N" w7 $end
$var wire 1 O" w8 $end
$var wire 1 P" w9 $end
$upscope $end
$upscope $end
$scope module MN3 $end
$var wire 2 Q" A [1:0] $end
$var wire 2 R" B [1:0] $end
$var wire 1 S" sel $end
$var wire 2 T" Y [1:0] $end
$scope module U1 $end
$var wire 2 U" A [1:0] $end
$var wire 2 V" B [1:0] $end
$var wire 1 S" Y $end
$var wire 1 W" w1 $end
$var wire 1 X" w10 $end
$var wire 1 Y" w11 $end
$var wire 1 Z" w12 $end
$var wire 1 [" w13 $end
$var wire 1 \" w2 $end
$var wire 1 ]" w5 $end
$var wire 1 ^" w6 $end
$var wire 1 _" w7 $end
$var wire 1 `" w8 $end
$var wire 1 a" w9 $end
$upscope $end
$upscope $end
$scope module MX0 $end
$var wire 2 b" A [1:0] $end
$var wire 2 c" B [1:0] $end
$var wire 2 d" Y [1:0] $end
$upscope $end
$scope module MX1 $end
$var wire 2 e" A [1:0] $end
$var wire 2 f" B [1:0] $end
$var wire 2 g" Y [1:0] $end
$upscope $end
$scope module MX2 $end
$var wire 2 h" A [1:0] $end
$var wire 2 i" B [1:0] $end
$var wire 2 j" Y [1:0] $end
$upscope $end
$scope module MX3 $end
$var wire 2 k" A [1:0] $end
$var wire 2 l" B [1:0] $end
$var wire 2 m" Y [1:0] $end
$upscope $end
$scope module SC0 $end
$var wire 2 n" A [1:0] $end
$var wire 2 o" Y [1:0] $end
$upscope $end
$scope module SC1 $end
$var wire 2 p" A [1:0] $end
$var wire 2 q" Y [1:0] $end
$upscope $end
$scope module SC2 $end
$var wire 2 r" A [1:0] $end
$var wire 2 s" Y [1:0] $end
$upscope $end
$scope module SC3 $end
$var wire 2 t" A [1:0] $end
$var wire 2 u" Y [1:0] $end
$upscope $end
$upscope $end
$scope module CTRL $end
$var wire 4 v" opcode [3:0] $end
$var reg 3 w" alu_op [2:0] $end
$var reg 1 / is_mov $end
$var reg 1 , reg_write $end
$upscope $end
$scope module IMEM $end
$var wire 4 x" addr [3:0] $end
$var wire 16 y" instr [15:0] $end
$upscope $end
$scope module RF $end
$var wire 1 $ clk $end
$var wire 4 z" rd_addr1 [3:0] $end
$var wire 4 {" rd_addr2 [3:0] $end
$var wire 8 |" rd_data1 [7:0] $end
$var wire 8 }" rd_data2 [7:0] $end
$var wire 1 % rst $end
$var wire 1 5 we $end
$var wire 4 ~" wr_addr [3:0] $end
$var wire 8 !# wr_data [7:0] $end
$var integer 32 "# i [31:0] $end
$upscope $end
$upscope $end
$upscope $end
$enddefinitions $end
#0
$dumpvars
b10000 "#
b0 !#
b0 ~"
b0 }"
b0 |"
b0 {"
b0 z"
b10010 y"
b0 x"
b0 w"
b0 v"
b1 u"
b0 t"
b1 s"
b0 r"
b1 q"
b0 p"
b1 o"
b0 n"
b0 m"
b0 l"
b0 k"
b0 j"
b0 i"
b0 h"
b0 g"
b0 f"
b0 e"
b0 d"
b0 c"
b0 b"
1a"
1`"
0_"
0^"
0]"
1\"
1["
1Z"
0Y"
1X"
1W"
b0 V"
b0 U"
b0 T"
1S"
b0 R"
b0 Q"
1P"
1O"
0N"
0M"
0L"
1K"
1J"
1I"
0H"
1G"
1F"
b0 E"
b0 D"
b0 C"
1B"
b0 A"
b0 @"
1?"
1>"
0="
0<"
0;"
1:"
19"
18"
07"
16"
15"
b0 4"
b0 3"
b0 2"
11"
b0 0"
b0 /"
1."
1-"
0,"
0+"
0*"
1)"
1("
1'"
0&"
1%"
1$"
b0 #"
b0 ""
b0 !"
1~
b0 }
b0 |
b0 {
b0 z
b0 y
b0 x
b0 w
b0 v
b0 u
b0 t
b0 s
b0 r
b0 q
b0 p
b0 o
b0 n
b0 m
b0 l
b0 k
b0 j
b0 i
b0 h
b0 g
b0 f
b0 e
b0 d
b0 c
b0 b
b0 a
b0 `
b0 _
b0 ^
b0 ]
b0 \
b0 [
b0 Z
b0 Y
b0 X
b0 W
b0 V
b0 U
b0 T
b0 S
b0 R
b0 Q
b0 P
b0 O
b0 N
b0 M
b0 L
b0 K
b0 J
b0 I
b0 H
b0 G
b0 F
b1 E
b1 D
b1 C
b1 B
b0 A
b0 @
b0 ?
b0 >
b0 =
b0 <
b0 ;
0:
09
b0 8
b0 7
b0 6
05
b0 4
b0 3
b0 2
01
b10010 0
0/
b0 .
b0 -
1,
b0 +
b0 *
b0 )
b0 (
1'
b0 &
1%
0$
b0 #
b1 "
b0 !
$end
#5
b1 "
b10000 "#
1$
#10
0$
#15
b1 "
b10000 "#
1$
#20
0$
#25
b1 "
b10000 "#
1$
#30
0$
#35
b1 "
b10000 "#
1$
#40
0$
0%
#45
b1 (
b1 }"
b1 )
b1 {"
b10 -
1:
b110000000000000 0
b110000000000000 y"
b1 >
b1 x"
b10010 =
1$
#46
b1 &
#50
0$
#55
b0 I
b0 !"
1&"
1~
1("
1,"
0%"
1+"
0'"
0'
b1 2
b1 P
0,
b1 M
b1 d"
b1 N
b1 b
b1 V
b1 h
b110 .
b110 v"
b0 (
b0 }"
b0 )
b0 {"
b0 -
b1 c"
b1 }
b1 #"
b1 g
b1 ]
b1 e
b10 >
b10 x"
b110000000000000 =
b1 <
b1 @
b1 R
b10010 8
15
1$
#56
b10 &
#60
0$
#65
0&"
0,"
1%"
0+"
1'"
1'
b0 2
b0 P
b0 M
b0 d"
b0 N
b0 b
b0 V
b0 h
b0 c"
b0 }
b0 #"
b0 g
b0 ]
b0 e
b10 4
b10 ~"
b1 6
b1 !#
0:
b0 <
b0 @
b0 R
b110000000000000 8
b11000100000000 0
b11000100000000 y"
b11 >
b11 x"
1$
#66
b11 &
#70
0$
#75
1/
1,
b11 .
b11 v"
b1 *
b1 |"
b1 +
b1 z"
b1 #
b11001000000001 0
b11001000000001 y"
b100 >
b100 x"
b11000100000000 =
05
b0 4
b0 ~"
b0 6
b0 !#
1$
#76
b100 &
#80
0$
#85
0~
0("
0%"
0)"
0'"
b1 M
b1 d"
b0 I
b0 !"
0'
b1 2
b1 P
b1 N
b1 b
b1 V
b1 h
b1 b"
b1 |
b1 ""
b10 E
b10 o"
b1 n"
b1 g
b1 a
b1 d
b10 +
b10 z"
b1 -
19
1:
b1 ;
b1 ?
b1 Q
b11000100000000 8
b110000000000000 0
b110000000000000 y"
b101 >
b101 x"
b11001000000001 =
1$
#86
b101 &
#90
0$
#95
0/
0,
b110 .
b110 v"
b0 *
b0 |"
b0 +
b0 z"
b0 -
b10010 0
b10010 y"
b110 >
b110 x"
b110000000000000 =
b11001000000001 8
15
b1 6
b1 !#
1$
#96
b110 &
#100
0$
#105
1~
1("
1%"
1)"
1'"
b0 M
b0 d"
1'
b0 2
b0 P
b0 N
b0 b
b0 V
b0 h
1,
b0 b"
b0 |
b0 ""
b1 E
b1 o"
b0 n"
b0 g
b0 a
b0 d
b0 .
b0 v"
b1 )
b1 {"
b10 -
b1 4
b1 ~"
09
0:
b0 ;
b0 ?
b0 Q
b110000000000000 8
b110000000000000 0
b110000000000000 y"
b111 >
b111 x"
b10010 =
b1 *
b1 |"
b1 (
b1 }"
b1 !
1$
#106
b111 &
#110
0$
#115
0)"
0,
b1 M
b1 d"
b1 I
b1 !"
0'
b10 2
b10 P
b10 N
b10 b
b10 V
b10 h
b110 .
b110 v"
b0 )
b0 {"
b0 -
b1 c"
b1 }
b1 #"
b1 ]
b1 e
b1 b"
b1 |
b1 ""
b10 E
b10 o"
b1 n"
b10 g
b1 a
b1 d
b1000 >
b1000 x"
b110000000000000 =
1:
b1 <
b1 @
b1 R
b1 ;
b1 ?
b1 Q
b10010 8
05
b0 4
b0 ~"
b0 6
b0 !#
1$
#116
b1000 &
#120
0$
#125
15
b10 4
b10 ~"
b10 6
b10 !#
0:
b110000000000000 8
b11000100000000 0
b11000100000000 y"
b1001 >
b1001 x"
1$
#126
b1001 &
#130
0$
#135
1/
1,
b11 .
b11 v"
b1 +
b1 z"
b10 #
b11001000000001 0
b11001000000001 y"
b1010 >
b1010 x"
b11000100000000 =
05
b0 4
b0 ~"
1$
#136
b1010 &
#140
0$
#145
b10 *
b10 |"
b10 +
b10 z"
b1 -
19
1:
b11000100000000 8
b110000000000000 0
b110000000000000 y"
b1011 >
b1011 x"
b11001000000001 =
1$
#146
b1011 &
#150
0$
#155
0~
0("
0-"
1+"
0%"
0$"
1)"
0."
0'"
0/
0,
b10 M
b10 d"
b1 I
b1 !"
b11 2
b11 P
b11 N
b11 b
b11 V
b11 h
b110 .
b110 v"
b1 *
b1 |"
b0 +
b0 z"
b0 -
b10 b"
b10 |
b10 ""
b11 E
b11 o"
b10 n"
b11 g
b10 a
b10 d
b10010 0
b10010 y"
b1100 >
b1100 x"
b110000000000000 =
b10 ;
b10 ?
b10 Q
b11001000000001 8
15
b1 6
b1 !#
1$
#156
b1100 &
#160
0$
#165
1~
1("
1-"
0+"
1%"
1$"
0)"
1."
1'"
b1 M
b1 d"
b10 2
b10 P
b10 N
b10 b
b10 V
b10 h
1,
b1 b"
b1 |
b1 ""
b10 E
b10 o"
b1 n"
b10 g
b1 a
b1 d
b0 .
b0 v"
b1 )
b1 {"
b10 -
b1 4
b1 ~"
b10 6
b10 !#
09
0:
b1 ;
b1 ?
b1 Q
b110000000000000 8
b110000000000000 0
b110000000000000 y"
b1101 >
b1101 x"
b10010 =
1$
#166
b1101 &
#170
0$
#175
0,
b110 .
b110 v"
b0 )
b0 {"
b0 -
b1 (
b1 }"
b10 "
b1110 >
b1110 x"
b110000000000000 =
1:
b10010 8
05
b0 4
b0 ~"
1$
#176
b1110 &
#180
0$
#185
15
b10 4
b10 ~"
0:
b110000000000000 8
b1111 >
b1111 x"
1$
#186
b1111 &
#190
0$
#195
b10010 0
b10010 y"
b0 >
b0 x"
05
b0 4
b0 ~"
1$
#196
b10000 &
#200
0$
#205
1,
b0 .
b0 v"
b10 (
b10 }"
b1 )
b1 {"
b10 -
b110000000000000 0
b110000000000000 y"
b1 >
b1 x"
b10010 =
1$
#206
b10001 &
#210
0$
#215
1&"
0%"
1*"
0."
0'"
b11 2
b11 P
0,
b10 M
b10 d"
b11 N
b11 b
b11 V
b11 h
b110 .
b110 v"
b1 (
b1 }"
b0 )
b0 {"
b0 -
b10 c"
b10 }
b10 #"
b11 g
b10 ]
b10 e
b10 >
b10 x"
b110000000000000 =
1:
b10 <
b10 @
b10 R
b10010 8
1$
#216
b10010 &
#220
0$
#225
0&"
1%"
0*"
1."
1'"
b10 2
b10 P
b1 M
b1 d"
b10 N
b10 b
b10 V
b10 h
b1 c"
b1 }
b1 #"
b10 g
b1 ]
b1 e
15
b10 4
b10 ~"
b11 6
b11 !#
0:
b1 <
b1 @
b1 R
b110000000000000 8
b11000100000000 0
b11000100000000 y"
b11 >
b11 x"
1$
#226
b10011 &
#230
0$
#235
1/
1,
b11 .
b11 v"
b10 *
b10 |"
b1 +
b1 z"
b11 #
b11001000000001 0
b11001000000001 y"
b100 >
b100 x"
b11000100000000 =
05
b0 4
b0 ~"
b10 6
b10 !#
1$
#236
b10100 &
#240
0$
#245
0~
0("
0-"
1+"
0%"
0$"
1)"
0."
0'"
b10 M
b10 d"
b1 I
b1 !"
b11 2
b11 P
b11 N
b11 b
b11 V
b11 h
b10 b"
b10 |
b10 ""
b11 E
b11 o"
b10 n"
b11 g
b10 a
b10 d
b11 *
b11 |"
b10 +
b10 z"
b1 -
19
1:
b10 ;
b10 ?
b10 Q
b11000100000000 8
b110000000000000 0
b110000000000000 y"
b101 >
b101 x"
b11001000000001 =
1$
#246
b10101 &
#250
0$
#255
0+"
0)"
1'"
b1 U
b1 n
0/
0,
b11 M
b11 d"
0'
b100 2
b100 P
b100 N
b100 b
b0 V
b0 h
b1 m
b1 Y
b1 i
b1 l
b110 .
b110 v"
b1 *
b1 |"
b0 +
b0 z"
b0 -
b11 b"
b11 |
b11 ""
b0 E
b0 o"
b11 n"
b100 g
b11 a
b11 d
b10010 0
b10010 y"
b110 >
b110 x"
b110000000000000 =
b11 ;
b11 ?
b11 Q
b11001000000001 8
15
1$
#256
b10110 &
#260
0$
